{"Symbol":{"0":"HEES","1":"SAIA","2":"XP","3":"CEG","4":"CBAY","5":"XPEV","6":"RIVN","7":"ZS","8":"RIOT","9":"RETA","10":"XPO","11":"RXRX","12":"ROIV","13":"CFLT","14":"SBS","15":"SCCO","16":"IE","17":"IAS","18":"CMPR","19":"HUBS","20":"RH","21":"CLS","22":"IGT","23":"YELP","24":"RXST","25":"HCCI","26":"RILY","27":"YPF","28":"GT","29":"CLH","30":"SDGR","31":"CHX","32":"SG","33":"COIN","34":"IMVT","35":"IMGN","36":"XPRO","37":"CPA","38":"SHAK","39":"SHC","40":"SHOP","41":"IONQ","42":"IOT","43":"SKYW","44":"CUBI","45":"CVNA","46":"SMCI","47":"ITRI","48":"JBL","49":"CXT","50":"JOE","51":"SPHR","52":"KDNY","53":"DASH","54":"DFH","55":"DECK","56":"SPXC","57":"KNSA","58":"KRNT","59":"STRL","60":"KRYS","61":"DICE","62":"DKNG","63":"DGII","64":"LI","65":"DO","66":"STVN","67":"LPRO","68":"AMWD","69":"ELF","70":"LRCX","71":"TDC","72":"DV","73":"LPG","74":"TBBK","75":"ANF","76":"TDW","77":"LMND","78":"APG","79":"EDU","80":"EH","81":"TEX","82":"NTNX","83":"APP","84":"APPF","85":"ENS","86":"NUVL","87":"THO","88":"NVDA","89":"ENVX","90":"TMDX","91":"ETRN","92":"ARCO","93":"ERO","94":"LZ","95":"TNK","96":"OC","97":"OII","98":"EXAS","99":"MATW","100":"META","101":"EXTR","102":"MDB","103":"TTD","104":"EXPI","105":"TPX","106":"ATI","107":"MARA","108":"FCNCA","109":"FLEX","110":"ONTO","111":"FICO","112":"ARHS","113":"ON","114":"PAM","115":"UBER","116":"AVGO","117":"MHO","118":"PACB","119":"MLTX","120":"AVDX","121":"U","122":"MLCO","123":"PCT","124":"FOR","125":"MLNK","126":"PARR","127":"MGNI","128":"FLNC","129":"UFPT","130":"PBF","131":"TXG","132":"OSTK","133":"MOD","134":"PHM","135":"FSLR","136":"MRVL","137":"MNSO","138":"UPST","139":"MNDY","140":"BBIO","141":"FTI","142":"FROG","143":"ACAD","144":"BCC","145":"PKX","146":"PDD","147":"BECN","148":"URBN","149":"VAL","150":"VECO","151":"GBX","152":"PLAB","153":"BLDR","154":"GE","155":"ADEA","156":"PLTR","157":"ACLS","158":"AEL","159":"VICR","160":"VRT","161":"GGAL","162":"GFF","163":"VIPS","164":"VIST","165":"PSTG","166":"BMI","167":"AFYA","168":"NE","169":"AEIS","170":"GKOS","171":"AI","172":"AEHR","173":"BMA","174":"QFIN","175":"ALGM","176":"W","177":"WFRD","178":"NEX","179":"CAAP","180":"GRBK","181":"AMPH","182":"NPO","183":"RCL","184":"RDFN","185":"CAMT","186":"CARS","187":"AMKR"},"Company Name":{"0":"H&E Equipment Services Inc. Common Stock","1":"Saia Inc. Common Stock","2":"XP Inc. Class A Common Stock","3":"Constellation Energy Corporation Common Stock ","4":"CymaBay Therapeutics Inc. Common Stock","5":"XPeng Inc. American depositary shares each representing two Class A ordinary shares","6":"Rivian Automotive Inc. Class A Common Stock","7":"Zscaler Inc. Common Stock","8":"Riot Platforms Inc. Common Stock ","9":"Reata Pharmaceuticals Inc. Class A Common Stock","10":"XPO Inc. Common Stock","11":"Recursion Pharmaceuticals Inc. Class A Common Stock","12":"Roivant Sciences Ltd. Common Shares","13":"Confluent Inc. Class A Common Stock","14":"Companhia de saneamento Basico Do Estado De Sao Paulo - Sabesp American Depositary Shares (Each repstg 250 Common Shares)","15":"Southern Copper Corporation Common Stock","16":"Ivanhoe Electric Inc. Common Stock","17":"Integral Ad Science Holding Corp. Common Stock","18":"Cimpress plc Ordinary Shares (Ireland)","19":"HubSpot Inc. Common Stock","20":"RH Common Stock","21":"Celestica Inc. Common Stock","22":"International Game Technology Ordinary Shares","23":"Yelp Inc. Common Stock","24":"RxSight Inc. Common Stock","25":"Heritage-Crystal Clean Inc. Common Stock","26":"B. Riley Financial Inc. Common Stock","27":"YPF Sociedad Anonima Common Stock","28":"The Goodyear Tire & Rubber Company Common Stock","29":"Clean Harbors Inc. Common Stock","30":"Schrodinger Inc. Common Stock","31":"ChampionX Corporation Common Stock ","32":"Sweetgreen Inc. Class A Common Stock","33":"Coinbase Global Inc. Class A Common Stock","34":"Immunovant Inc. Common Stock","35":"ImmunoGen Inc. Common Stock","36":"Expro Group Holdings N.V. Common Stock","37":"Copa Holdings S.A. Copa Holdings S.A. Class A Common Stock","38":"Shake Shack Inc. Class A Common Stock","39":"Sotera Health Company Common Stock","40":"Shopify Inc. Class A Subordinate Voting Shares","41":"IonQ Inc. Common Stock","42":"Samsara Inc. Class A Common Stock","43":"SkyWest Inc. Common Stock","44":"Customers Bancorp Inc Common Stock","45":"Carvana Co. Class A Common Stock","46":"Super Micro Computer Inc. Common Stock","47":"Itron Inc. Common Stock","48":"Jabil Inc. Common Stock","49":"Crane NXT Co. Common Stock","50":"St. Joe Company (The) Common Stock","51":"Sphere Entertainment Co. Class A Common Stock","52":"Chinook Therapeutics Inc. Common Stock","53":"DoorDash Inc. Class A Common Stock","54":"Dream Finders Homes Inc. Class A Common Stock","55":"Deckers Outdoor Corporation Common Stock","56":"SPX Technologies Inc. Common Stock","57":"Kiniksa Pharmaceuticals Ltd. Class A Common Stock","58":"Kornit Digital Ltd. Ordinary Shares","59":"Sterling Infrastructure Inc. Common Stock","60":"Krystal Biotech Inc. Common Stock","61":"DICE Therapeutics Inc. Common Stock","62":"DraftKings Inc. Class A Common Stock","63":"Digi International Inc. Common Stock","64":"Li Auto Inc. American Depositary Shares","65":"Diamond Offshore Drilling Inc. Common Stock","66":"Stevanato Group S.p.A. Ordinary Shares","67":"Open Lending Corporation Common Stock","68":"American Woodmark Corporation Common Stock","69":"e.l.f. Beauty Inc. Common Stock","70":"Lam Research Corporation Common Stock","71":"Teradata Corporation Common Stock","72":"DoubleVerify Holdings Inc. Common Stock","73":"Dorian LPG Ltd. Common Stock","74":"The Bancorp Inc Common Stock","75":"Abercrombie & Fitch Company Common Stock","76":"Tidewater Inc. Common Stock","77":"Lemonade Inc. Common Stock","78":"APi Group Corporation Common Stock","79":"New Oriental Education & Technology Group Inc. Sponsored ADR representing 10 Ordinary Share (Cayman Islands)","80":"EHang Holdings Limited ADS","81":"Terex Corporation Common Stock","82":"Nutanix Inc. Class A Common Stock","83":"Applovin Corporation Class A Common Stock","84":"AppFolio Inc. Class A Common Stock","85":"EnerSys Common Stock","86":"Nuvalent Inc. Class A Common Stock","87":"Thor Industries Inc. Common Stock","88":"NVIDIA Corporation Common Stock","89":"Enovix Corporation Common Stock","90":"TransMedics Group Inc. Common Stock","91":"Equitrans Midstream Corporation Common Stock ","92":"Arcos Dorados Holdings Inc. Class A Shares","93":"Ero Copper Corp. Common Shares","94":"LegalZoom.com Inc. Common Stock","95":"Teekay Tankers Ltd.","96":"Owens Corning Inc Common Stock New","97":"Oceaneering International Inc. Common Stock","98":"Exact Sciences Corporation Common Stock","99":"Matthews International Corporation Class A Common Stock","100":"Meta Platforms Inc. Class A Common Stock","101":"Extreme Networks Inc. Common Stock","102":"MongoDB Inc. Class A Common Stock","103":"The Trade Desk Inc. Class A Common Stock","104":"eXp World Holdings Inc. Common Stock","105":"Tempur Sealy International Inc. Common Stock","106":"ATI Inc. Common Stock","107":"Marathon Digital Holdings Inc. Common Stock","108":"First Citizens BancShares Inc. Class A Common Stock","109":"Flex Ltd. Ordinary Shares","110":"Onto Innovation Inc. Common Stock","111":"Fair Isaac Corproation Common Stock","112":"Arhaus Inc. Class A Common Stock","113":"ON Semiconductor Corporation Common Stock","114":"Pampa Energia S.A. Pampa Energia S.A.","115":"Uber Technologies Inc. Common Stock","116":"Broadcom Inc. Common Stock","117":"M\/I Homes Inc. Common Stock","118":"Pacific Biosciences of California Inc. Common Stock","119":"MoonLake Immunotherapeutics Class A Ordinary Shares","120":"AvidXchange Holdings Inc. Common Stock","121":"Unity Software Inc. Common Stock","122":"Melco Resorts & Entertainment Limited American Depositary Shares","123":"PureCycle Technologies Inc. Common stock","124":"Forestar Group Inc Common Stock ","125":"MeridianLink Inc. Common Stock","126":"Par Pacific Holdings Inc.  Common Stock","127":"Magnite Inc. Common Stock","128":"Fluence Energy Inc. Class A Common Stock","129":"UFP Technologies Inc. Common Stock","130":"PBF Energy Inc. Class A Common Stock","131":"10x Genomics Inc. Class A Common Stock","132":"Overstock.com Inc. Common Stock","133":"Modine Manufacturing Company Common Stock","134":"PulteGroup Inc. Common Stock","135":"First Solar Inc. Common Stock","136":"Marvell Technology Inc. Common Stock","137":"MINISO Group Holding Limited American Depositary Shares each representing four Ordinary Shares","138":"Upstart Holdings Inc. Common stock","139":"monday.com Ltd. Ordinary Shares","140":"BridgeBio Pharma Inc. Common Stock","141":"TechnipFMC plc Ordinary Share","142":"JFrog Ltd. Ordinary Shares","143":"ACADIA Pharmaceuticals Inc. Common Stock","144":"Boise Cascade L.L.C. Common Stock","145":"POSCO Holdings Inc. American Depositary Shares (Each representing 1\/4th of a share of Common Stock)","146":"PDD Holdings Inc. American Depositary Shares","147":"Beacon Roofing Supply Inc. Common Stock","148":"Urban Outfitters Inc. Common Stock","149":"Valaris Limited Common Shares","150":"Veeco Instruments Inc. Common Stock","151":"Greenbrier Companies Inc. (The) Common Stock","152":"Photronics Inc. Common Stock","153":"Builders FirstSource Inc. Common Stock","154":"General Electric Company Common Stock","155":"Adeia Inc. Common Stock","156":"Palantir Technologies Inc. Class A Common Stock","157":"Axcelis Technologies Inc. Common Stock","158":"American Equity Investment Life Holding Company Common Stock","159":"Vicor Corporation Common Stock","160":"Vertiv Holdings LLC Class A Common Stock","161":"Grupo Financiero Galicia S.A. American Depositary Shares","162":"Griffon Corporation Common Stock","163":"Vipshop Holdings Limited American Depositary Shares each representing two ordinary shares","164":"Vista Energy S.A.B. de C.V. American Depositary Shares each representing one series A share with no par value","165":"Pure Storage Inc. Class A Common Stock","166":"Badger Meter Inc. Common Stock","167":"Afya Limited Class A Common Shares","168":"Noble Corporation plc A Ordinary Shares","169":"Advanced Energy Industries Inc. Common Stock","170":"Glaukos Corporation Common Stock","171":"C3.ai Inc. Class A Common Stock","172":"Aehr Test Systems Common Stock","173":"Banco Macro S.A.  ADR (representing Ten Class B Common Shares)","174":"Qifu Technology Inc. American Depositary Shares","175":"Allegro MicroSystems Inc. Common Stock","176":"Wayfair Inc. Class A Common Stock","177":"Weatherford International plc Ordinary Shares","178":"NexTier Oilfield Solutions Inc. Common Stock","179":"Corporacion America Airports SA Common Shares","180":"Green Brick Partners Inc. Common Stock","181":"Amphastar Pharmaceuticals Inc. Common Stock","182":"EnPro Industries Inc","183":"Royal Caribbean Cruises Ltd. Common Stock","184":"Redfin Corporation Common Stock","185":"Camtek Ltd. Ordinary Shares","186":"Cars.com Inc. Common Stock ","187":"Amkor Technology Inc. Common Stock"},"Industry":{"0":"","1":"Trucking Freight\/Courier Services","2":"Investment Bankers\/Brokers\/Service","3":"Electric Utilities: Central","4":"Biotechnology: Pharmaceutical Preparations","5":"Auto Manufacturing","6":"Auto Manufacturing","7":"EDP Services","8":"Retail: Computer Software & Peripheral Equipment","9":"Biotechnology: Pharmaceutical Preparations","10":"Transportation Services","11":"Biotechnology: Pharmaceutical Preparations","12":"Biotechnology: Pharmaceutical Preparations","13":"EDP Services","14":"Water Supply","15":"Metal Mining","16":"Metal Mining","17":"Computer Software: Programming Data Processing","18":"Publishing","19":"Computer Software: Prepackaged Software","20":"Other Specialty Stores","21":"","22":"Services-Misc. Amusement & Recreation","23":"Other Consumer Services","24":"Biotechnology: Electromedical & Electrotherapeutic Apparatus","25":"Miscellaneous","26":"Investment Managers","27":"Integrated oil Companies","28":"Automotive Aftermarket","29":"Environmental Services","30":"Biotechnology: Pharmaceutical Preparations","31":"Industrial Machinery\/Components","32":"Restaurants","33":"Finance: Consumer Services","34":"Biotechnology: Biological Products (No Diagnostic Substances)","35":"Biotechnology: Pharmaceutical Preparations","36":"Oilfield Services\/Equipment","37":"Air Freight\/Delivery Services","38":"Restaurants","39":"Medical Specialities","40":"Computer Software: Prepackaged Software","41":"Wholesale Distributors","42":"Retail: Computer Software & Peripheral Equipment","43":"Air Freight\/Delivery Services","44":"Major Banks","45":"Retail-Auto Dealers and Gas Stations","46":"Computer Manufacturing","47":"Electrical Products","48":"Electrical Products","49":"Office Equipment\/Supplies\/Services","50":"Homebuilding","51":"Movies\/Entertainment","52":"Biotechnology: Pharmaceutical Preparations","53":"Industrial Machinery\/Components","54":"Homebuilding","55":"Shoe Manufacturing","56":"Industrial Machinery\/Components","57":"Biotechnology: Pharmaceutical Preparations","58":"Industrial Machinery\/Components","59":"Military\/Government\/Technical","60":"Biotechnology: Biological Products (No Diagnostic Substances)","61":"Biotechnology: Pharmaceutical Preparations","62":"Services-Misc. Amusement & Recreation","63":"Computer Communications Equipment","64":"Auto Manufacturing","65":"Oil & Gas Production","66":"Containers\/Packaging","67":"Finance: Consumer Services","68":"Forest Products","69":"Package Goods\/Cosmetics","70":"Industrial Machinery\/Components","71":"Computer Software: Prepackaged Software","72":"Computer Software: Prepackaged Software","73":"Marine Transportation","74":"Major Banks","75":"Clothing\/Shoe\/Accessory Stores","76":"Marine Transportation","77":"Property-Casualty Insurers","78":"Engineering & Construction","79":"Educational Services","80":"Air Freight\/Delivery Services","81":"Construction\/Ag Equipment\/Trucks","82":"EDP Services","83":"EDP Services","84":"Computer Software: Prepackaged Software","85":"Industrial Machinery\/Components","86":"Biotechnology: Pharmaceutical Preparations","87":"Homebuilding","88":"Semiconductors","89":"Industrial Machinery\/Components","90":"Biotechnology: Electromedical & Electrotherapeutic Apparatus","91":"Natural Gas Distribution","92":"Restaurants","93":"","94":"EDP Services","95":"Marine Transportation","96":"Industrial Machinery\/Components","97":"Oilfield Services\/Equipment","98":"Medical Specialities","99":"Metal Fabrications","100":"Computer Software: Programming Data Processing","101":"Telecommunications Equipment","102":"Retail: Computer Software & Peripheral Equipment","103":"EDP Services","104":"Real Estate","105":"Home Furnishings","106":"Steel\/Iron Ore","107":"EDP Services","108":"Major Banks","109":"Electrical Products","110":"Industrial Machinery\/Components","111":"Business Services","112":"Other Specialty Stores","113":"Semiconductors","114":"Electric Utilities: Central","115":"Business Services","116":"Semiconductors","117":"Homebuilding","118":"Biotechnology: Laboratory Analytical Instruments","119":"Biotechnology: Pharmaceutical Preparations","120":"EDP Services","121":"Retail: Computer Software & Peripheral Equipment","122":"Hotels\/Resorts","123":"Environmental Services","124":"Real Estate","125":"Computer Software: Prepackaged Software","126":"Oil & Gas Production","127":"Advertising","128":"Industrial Machinery\/Components","129":"Medical\/Dental Instruments","130":"Integrated oil Companies","131":"Biotechnology: Laboratory Analytical Instruments","132":"Catalog\/Specialty Distribution","133":"Auto Parts:O.E.M.","134":"Homebuilding","135":"Semiconductors","136":"Semiconductors","137":"Department\/Specialty Retail Stores","138":"Finance: Consumer Services","139":"Computer Software: Prepackaged Software","140":"Biotechnology: Pharmaceutical Preparations","141":"Metal Fabrications","142":"Computer Software: Prepackaged Software","143":"Biotechnology: Pharmaceutical Preparations","144":"RETAIL: Building Materials","145":"Steel\/Iron Ore","146":"Business Services","147":"RETAIL: Building Materials","148":"Clothing\/Shoe\/Accessory Stores","149":"Oil & Gas Production","150":"Semiconductors","151":"Railroads","152":"Semiconductors","153":"RETAIL: Building Materials","154":"Consumer Electronics\/Appliances","155":"Computer Software: Prepackaged Software","156":"Retail: Computer Software & Peripheral Equipment","157":"Industrial Machinery\/Components","158":"Life Insurance","159":"Industrial Machinery\/Components","160":"Industrial Machinery\/Components","161":"Commercial Banks","162":"Building Products","163":"Catalog\/Specialty Distribution","164":"Oil & Gas Production","165":"Electronic Components","166":"Industrial Machinery\/Components","167":"Educational Services","168":"Oil & Gas Production","169":"Industrial Machinery\/Components","170":"Medical\/Dental Instruments","171":"Computer Software: Prepackaged Software","172":"Electrical Products","173":"Commercial Banks","174":"Finance: Consumer Services","175":"Semiconductors","176":"Catalog\/Specialty Distribution","177":"Metal Fabrications","178":"Oilfield Services\/Equipment","179":"Aerospace","180":"Homebuilding","181":"Biotechnology: Pharmaceutical Preparations","182":"Metal Fabrications","183":"Marine Transportation","184":"Real Estate","185":"Electronic Components","186":"","187":"Semiconductors"},"RS":{"0":90,"1":96,"2":96,"3":92,"4":98,"5":97,"6":95,"7":91,"8":96,"9":98,"10":97,"11":99,"12":96,"13":91,"14":90,"15":91,"16":94,"17":92,"18":94,"19":91,"20":92,"21":95,"22":90,"23":91,"24":97,"25":92,"26":94,"27":99,"28":91,"29":90,"30":95,"31":91,"32":97,"33":95,"34":99,"35":100,"36":92,"37":93,"38":92,"39":93,"40":94,"41":99,"42":94,"43":96,"44":98,"45":100,"46":100,"47":90,"48":94,"49":91,"50":94,"51":93,"52":98,"53":91,"54":96,"55":91,"56":90,"57":96,"58":90,"59":97,"60":93,"61":98,"62":96,"63":92,"64":94,"65":95,"66":91,"67":91,"68":94,"69":97,"70":90,"71":91,"72":91,"73":91,"74":92,"75":97,"76":96,"77":96,"78":90,"79":95,"80":99,"81":93,"82":95,"83":93,"84":92,"85":91,"86":97,"87":91,"88":98,"89":98,"90":94,"91":97,"92":93,"93":94,"94":93,"95":92,"96":91,"97":94,"98":97,"99":93,"100":91,"101":96,"102":94,"103":92,"104":97,"105":92,"106":91,"107":92,"108":95,"109":93,"110":92,"111":90,"112":96,"113":93,"114":92,"115":96,"116":94,"117":95,"118":97,"119":100,"120":96,"121":92,"122":96,"123":95,"124":96,"125":90,"126":94,"127":94,"128":97,"129":96,"130":91,"131":90,"132":93,"133":98,"134":93,"135":94,"136":93,"137":99,"138":100,"139":92,"140":99,"141":96,"142":91,"143":94,"144":93,"145":97,"146":93,"147":91,"148":92,"149":91,"150":90,"151":94,"152":94,"153":96,"154":93,"155":98,"156":98,"157":98,"158":91,"159":98,"160":97,"161":97,"162":93,"163":93,"164":97,"165":94,"166":90,"167":91,"168":93,"169":91,"170":94,"171":99,"172":99,"173":96,"174":92,"175":95,"176":97,"177":98,"178":90,"179":96,"180":95,"181":96,"182":92,"183":98,"184":98,"185":96,"186":90,"187":91},"Price":{"0":43.9700012207,"1":410.8099975586,"2":26.3999996185,"3":95.4199981689,"4":11.720000267,"5":20.2199993134,"6":26.0499992371,"7":155.25,"8":17.6000003815,"9":108.5500030518,"10":70.5699996948,"11":12.9099998474,"12":10.8000001907,"13":34.0600013733,"14":11.8500003815,"15":83.9700012207,"16":15.9499998093,"17":19.3700008392,"18":68.0999984741,"19":548.3699951172,"20":381.1799926758,"21":18.0100002289,"22":33.2999992371,"23":42.8499984741,"24":32.3600006104,"25":47.1199989319,"26":56.1599998474,"27":14.3500003815,"28":15.8699998856,"29":165.4900054932,"30":47.7599983215,"31":33.6699981689,"32":15.4499998093,"33":92.6900024414,"34":21.7299995422,"35":18.4599990845,"36":21.7399997711,"37":118.4000015259,"38":76.4700012207,"39":18.7700004578,"40":63.9599990845,"41":15.529999733,"42":26.0100002289,"43":39.6500015259,"44":41.7799987793,"45":40.4599990845,"46":327.3399963379,"47":75.7699966431,"48":108.9499969482,"49":57.8800010681,"50":64.5599975586,"51":41.0800018311,"52":38.9300003052,"53":86.0400009155,"54":23.9400005341,"55":537.0200195312,"56":83.5299987793,"57":18.5100002289,"58":29.3999996185,"59":58.75,"60":121.2600021362,"61":46.9500007629,"62":30.9599990845,"63":41.6399993896,"64":38.9900016785,"65":15.3900003433,"66":30.4599990845,"67":11.1999998093,"68":76.8199996948,"69":111.4899978638,"70":701.950012207,"71":54.9399986267,"72":40.25,"73":28.2399997711,"74":39.0600013733,"75":38.9599990845,"76":58.4799995422,"77":20.7600002289,"78":28.1599998474,"79":52.6500015259,"80":18.5100002289,"81":56.7599983215,"82":29.8299999237,"83":29.9799995422,"84":175.8200073242,"85":106.9100036621,"86":46.4300003052,"87":111.8700027466,"88":459.0,"89":18.6399993896,"90":89.5199966431,"91":10.1099996567,"92":11.3000001907,"93":22.6599998474,"94":14.5799999237,"95":41.0400009155,"96":139.0599975586,"97":21.0799999237,"98":97.2099990845,"99":47.7900009155,"100":311.7099914551,"101":27.3400001526,"102":403.5799865723,"103":85.3799972534,"104":22.75,"105":46.0600013733,"106":46.4500007629,"107":15.970000267,"108":1420.8000488281,"109":27.0,"110":117.3000030518,"111":820.3200073242,"112":11.0200004578,"113":102.1100006104,"114":41.2400016785,"115":46.6100006104,"116":893.5300292969,"117":97.2099990845,"118":13.1899995804,"119":60.2200012207,"120":12.0500001907,"121":43.2099990845,"122":12.8500003815,"123":10.5799999237,"124":29.1000003815,"125":21.9400005341,"126":30.5400009155,"127":14.1199998856,"128":27.7600002289,"129":191.0899963379,"130":46.0099983215,"131":60.7099990845,"132":35.0200004578,"133":35.3899993896,"134":83.6399993896,"135":198.8000030518,"136":63.8899993896,"137":20.3799991608,"138":58.9399986267,"139":175.3099975586,"140":32.1300010681,"141":17.5599994659,"142":28.9400005341,"143":29.0200004578,"144":99.1600036621,"145":115.0199966431,"146":84.5299987793,"147":82.9199981689,"148":35.0099983215,"149":74.1999969482,"150":26.9799995422,"151":44.7299995422,"152":25.4300003052,"153":141.5,"154":115.4199981689,"155":11.6899995804,"156":16.1499996185,"157":182.75,"158":53.8899993896,"159":95.1399993896,"160":25.3199996948,"161":16.5200004578,"162":41.5999984741,"163":16.9599990845,"164":25.3199996948,"165":38.0099983215,"166":162.5200042725,"167":15.4499998093,"168":51.4300003052,"169":120.2200012207,"170":77.8000030518,"171":38.2099990845,"172":48.9900016785,"173":24.6299991608,"174":18.8099994659,"175":49.2999992371,"176":68.7300033569,"177":79.0,"178":11.5799999237,"179":13.5600004196,"180":53.7799987793,"181":60.6100006104,"182":136.3600006104,"183":109.6800003052,"184":13.9499998093,"185":46.0,"186":22.2199993134,"187":29.0599994659},"Market Cap":{"0":1599705811,"1":10899930530,"2":14797693680,"3":31187574518,"4":1142854458,"5":8727930648,"6":24469677011,"7":22649603832,"8":3081372800,"9":4076209029,"10":8176029407,"11":2483359596,"12":8191015380,"13":10086256295,"14":8099591948,"15":64917347146,"16":1482721315,"17":3000950905,"18":1792573555,"19":27220367887,"20":8405861789,"21":2190768674,"22":6782877000,"23":2949716741,"24":1099653540,"25":1147369880,"26":1580097318,"27":5643295106,"28":4498006280,"29":8953690984,"30":3416267833,"31":6618912674,"32":1721935548,"33":21741557619,"34":2833774293,"35":4173259935,"36":2360793754,"37":3372032000,"38":3230822018,"39":5302835193,"40":81799444079,"41":3121969810,"42":13747101064,"43":1999995087,"44":1305623538,"45":7664909540,"46":17181583626,"47":3441686238,"48":14455955901,"49":3283541834,"50":3768498902,"51":1419674682,"52":2604003135,"53":33432078395,"54":2229567631,"55":14048360499,"56":3800767776,"57":2587679860,"58":1470000000,"59":1808893406,"60":3128476230,"61":2240950590,"62":24820143265,"63":1493648703,"64":40216455638,"65":1559897589,"66":1038686000,"67":1351324285,"68":1277923362,"69":6005639857,"70":94300295724,"71":5554434000,"72":6693103149,"73":1140408295,"74":2136246279,"75":1950531855,"76":2974559293,"77":1442627742,"78":6623595264,"79":8934526938,"80":1077799799,"81":3848328000,"82":7032701888,"83":10927043395,"84":6239119510,"85":4373629727,"86":2638188351,"87":5963585425,"88":1133730000000,"89":2948104450,"90":2914202748,"91":4379480130,"92":1475667000,"93":2096512536,"94":2782255094,"95":1202882400,"96":12530606350,"97":2124232317,"98":17535533714,"99":1455595849,"100":798829202318,"101":3526786866,"102":28485231726,"103":41737971249,"104":3490815078,"105":7925561242,"106":5971043452,"107":2673376962,"108":20630006054,"109":12001325742,"110":5741303631,"111":20502352917,"112":1543226584,"113":44098534569,"114":2276061457,"115":94330584021,"116":368746789930,"117":2705297529,"118":3296067619,"119":3173660904,"120":2425054896,"121":16361792174,"122":5868390017,"123":1731632790,"124":1452198048,"125":1769359330,"126":1864116951,"127":1914312392,"128":4872351892,"129":1454996905,"130":5801726237,"131":7054023787,"132":1582870241,"133":1842583110,"134":18354418023,"135":21236943991,"136":43170473000,"137":6438498940,"138":4872628563,"139":8369299400,"140":5156897098,"141":7753846192,"142":2948524204,"143":4719389108,"144":3925727047,"145":34896689354,"146":111544697478,"147":5286013845,"148":3245351203,"149":5578445040,"150":1393825354,"151":1427912972,"152":1588729180,"153":18135899916,"154":125620611036,"155":1243064777,"156":34212885070,"157":5977959008,"158":4200254340,"159":4206546885,"160":9614922356,"161":2436191333,"162":2379737568,"163":9937007142,"164":2238452074,"165":11708801891,"166":4764745271,"167":1448017724,"168":3448401506,"169":4512306824,"170":3750636238,"171":4287533554,"172":1388288859,"173":1574875229,"174":3035859362,"175":9453618424,"176":7717789090,"177":5693077093,"178":2669168415,"179":2180990400,"180":2447440461,"181":2925889686,"182":2846940852,"183":28049197417,"184":1545732289,"185":2049760000,"186":1482554974,"187":7138318916},"50-day Average Volume":{"0":236460,"1":513656,"2":6514470,"3":2282818,"4":2026778,"5":19866438,"6":52350402,"7":2758730,"8":23576742,"9":742696,"10":1822028,"11":6579540,"12":5254514,"13":4537314,"14":1220876,"15":1139816,"16":471086,"17":964092,"18":120690,"19":513328,"20":879312,"21":896646,"22":1434912,"23":723214,"24":455866,"25":149368,"26":273920,"27":1847890,"28":4603630,"29":385158,"30":1632312,"31":1520178,"32":2060662,"33":16966121,"34":1172308,"35":5427776,"36":716002,"37":625416,"38":710856,"39":1059162,"40":12915313,"41":12255476,"42":3907820,"43":646966,"44":505462,"45":32733967,"46":3056070,"47":328290,"48":1108318,"49":413156,"50":195946,"51":507256,"52":1613706,"53":2995784,"54":298504,"55":491484,"56":249944,"57":531840,"58":331812,"59":325992,"60":337628,"61":1947024,"62":10719530,"63":280428,"64":7082530,"65":1241612,"66":310696,"67":648426,"68":122832,"69":1083666,"70":1380972,"71":918982,"72":1353562,"73":523756,"74":379134,"75":2086234,"76":799736,"77":1711282,"78":937252,"79":1607804,"80":1036468,"81":712180,"82":1664898,"83":2463694,"84":115768,"85":294744,"86":296512,"87":645724,"88":52786594,"89":7451458,"90":483178,"91":8378930,"92":1539102,"93":120942,"94":1272072,"95":425076,"96":880864,"97":841128,"98":1639684,"99":116828,"100":25723430,"101":2074912,"102":1942682,"103":4387558,"104":1596776,"105":1713076,"106":1131766,"107":41046910,"108":107806,"109":4004540,"110":362948,"111":189506,"112":644654,"113":6969320,"114":160920,"115":21806135,"116":3393740,"117":330250,"118":3619032,"119":847036,"120":2338548,"121":15100238,"122":3007962,"123":1871624,"124":170604,"125":172202,"126":912358,"127":1359744,"128":1288360,"129":133680,"130":2332000,"131":899224,"132":2509600,"133":557338,"134":2832870,"135":1759584,"136":16015306,"137":1186632,"138":11635352,"139":887380,"140":3327442,"141":6671174,"142":925478,"143":1628532,"144":321804,"145":357294,"146":10141600,"147":487368,"148":1963190,"149":851336,"150":670518,"151":350162,"152":692454,"153":2229292,"154":5345944,"155":612460,"156":82848281,"157":530264,"158":924448,"159":519172,"160":5405710,"161":787456,"162":447558,"163":4913358,"164":740542,"165":4690752,"166":183612,"167":229966,"168":1589384,"169":202708,"170":536074,"171":33323063,"172":1295666,"173":310522,"174":951150,"175":1450468,"176":5189422,"177":779688,"178":3099972,"179":135820,"180":437532,"181":453506,"182":135844,"183":3841254,"184":3306342,"185":190318,"186":513618,"187":1038954},"% Below 52-week High":{"0":22.1356450846,"1":4.9028918358,"2":4.5898098356,"3":2.8705230365,"4":6.239997864,"5":21.9606356102,"6":36.2457189498,"7":20.0607589722,"8":14.7699739395,"9":35.093277295,"10":3.1297190188,"11":22.9253740454,"12":10.0749359642,"13":17.3702053049,"14":1.6597478714,"15":2.0415291406,"16":4.4337938328,"17":5.7420883737,"18":5.0474087087,"19":4.0623532397,"20":3.3274175309,"21":15.8804286366,"22":2.0300110706,"23":5.4083918894,"24":4.1753017163,"25":1.7924157318,"26":7.5098816742,"27":11.3650377918,"28":3.8181825115,"29":4.0860058577,"30":19.3788009428,"31":6.860309353,"32":28.6703609912,"33":20.3009437305,"34":13.5296476634,"35":10.7781581223,"36":9.5673886394,"37":2.0029783762,"38":5.1005197063,"39":8.0352745821,"40":10.4577921259,"41":13.7701291893,"42":15.8524741867,"43":13.7668518358,"44":7.1555582682,"45":30.301465832,"46":3.0936391433,"47":1.5078686558,"48":5.4663800883,"49":2.3287190886,"50":2.1669986989,"51":6.4875897312,"52":1.5427407557,"53":5.3048636193,"54":12.2433998017,"55":4.6094783858,"56":2.7023893077,"57":10.3631950174,"58":21.3693511139,"59":3.0207989435,"60":7.9969634778,"61":0.3396290323,"62":4.5916823282,"63":4.6703310678,"64":8.9656743439,"65":6.8401916265,"66":11.2729417871,"67":6.5888256105,"68":1.7772667245,"69":7.5615638307,"70":3.0549515645,"71":3.9510513519,"72":4.1438437723,"73":3.8147146761,"74":5.9248521838,"75":3.8024713963,"76":6.5665449078,"77":37.0336662757,"78":2.1542743315,"79":6.3000506747,"80":15.0917420693,"81":13.5283389374,"82":11.5624075787,"83":26.084813752,"84":10.2501238774,"85":5.6731924633,"86":5.9550328029,"87":3.0337152235,"88":4.5499916819,"89":29.1254776061,"90":10.1475492893,"91":3.5305376269,"92":1.482125626,"93":2.9134539529,"94":2.9940124837,"95":12.4012787289,"96":3.2087439559,"97":11.465771005,"98":3.5327983681,"99":2.1899285397,"100":4.4420627054,"101":4.405593872,"102":8.0683401885,"103":6.8514103716,"104":8.9271417134,"105":2.3531876759,"106":1.9214510918,"107":19.6680067052,"108":2.5501002189,"109":6.5743944637,"110":5.2733561723,"111":4.6139526367,"112":27.832348017,"113":3.1122491599,"114":9.6208597885,"115":3.7579999785,"116":3.2117215173,"117":3.340957458,"118":9.3470819216,"119":5.0157709453,"120":2.4291482534,"121":26.2879578907,"122":11.0726617197,"123":9.8039222191,"124":3.0969018265,"125":3.3054185364,"126":1.8322053504,"127":10.2352200534,"128":11.3665382219,"129":6.8217298918,"130":6.1020442418,"131":4.4238049677,"132":10.2051270313,"133":7.0640772332,"134":2.7554942569,"135":14.3103435122,"136":6.0302994711,"137":5.4731022226,"138":12.3177646137,"139":7.3169455149,"140":11.6336604288,"141":8.3028748517,"142":6.4641223849,"143":14.6219462848,"144":3.4093087258,"145":13.5772810556,"146":20.5395762556,"147":3.4129316612,"148":3.0462522251,"149":7.2500038148,"150":2.7046536524,"151":1.6923086985,"152":5.7449951623,"153":5.1672139937,"154":2.153273848,"155":3.4682115574,"156":15.0000020079,"157":5.6482007331,"158":0.7550655808,"159":3.2933529278,"160":6.3263052357,"161":9.923661626,"162":2.8264459843,"163":8.2251131791,"164":9.0843817063,"165":3.0109764698,"166":2.6826321722,"167":9.2244429536,"168":2.4838826219,"169":2.0690768812,"170":3.0891840411,"171":21.8129750675,"172":9.2777746694,"173":10.2405278397,"174":26.2063575288,"175":7.0688044541,"176":9.9803492379,"177":5.0937049495,"178":3.4195168999,"179":5.8333304194,"180":9.3086023958,"181":4.8807272279,"182":5.8677339428,"183":2.8950860512,"184":21.0972861465,"185":4.4652128764,"186":2.2867224565,"187":7.3932458066},"10-day SMA":{"0":46.89,"1":401.11,"2":25.64,"3":96.23,"4":11.71,"5":16.74,"6":25.59,"7":153.75,"8":18.24,"9":115.16,"10":67.64,"11":14.18,"12":11.22,"13":36.49,"14":11.59,"15":80.21,"16":15.91,"17":19.89,"18":65.14,"19":551.33,"20":379.55,"21":16.91,"22":33.17,"23":42.56,"24":31.88,"25":45.43,"26":56.21,"27":15.24,"28":15.8,"29":167.5,"30":51.47,"31":34.55,"32":15.38,"33":100.61,"34":22.59,"35":18.91,"36":21.97,"37":118.54,"38":77.84,"39":18.89,"40":66.1,"41":15.47,"42":27.28,"43":41.28,"44":40.41,"45":44.31,"46":314.01,"47":75.47,"48":112.08,"49":57.58,"50":56.12,"51":39.1,"52":39.14,"53":85.52,"54":25.51,"55":544.47,"56":82.06,"57":16.97,"58":29.6,"59":58.54,"60":123.05,"61":46.85,"62":31.16,"63":41.49,"64":38.43,"65":15.67,"66":32.15,"67":11.3,"68":75.75,"69":114.11,"70":655.01,"71":55.57,"72":40.85,"73":26.72,"74":38.77,"75":37.66,"76":59.42,"77":22.03,"78":28.36,"79":48.63,"80":18.62,"81":60.67,"82":29.6,"83":28.94,"84":185.14,"85":109.5,"86":45.49,"87":111.4,"88":459.25,"89":20.14,"90":91.8,"91":9.43,"92":10.86,"93":22.2,"94":14.17,"95":39.26,"96":134.92,"97":22.92,"98":96.65,"99":47.52,"100":305.73,"101":27.41,"102":413.87,"103":86.18,"104":22.97,"105":45.88,"106":45.94,"107":16.77,"108":1388.03,"109":28.1,"110":111.74,"111":838.97,"112":11.27,"113":101.13,"114":43.64,"115":47.04,"116":900.62,"117":93.91,"118":13.35,"119":57.82,"120":12.0,"121":44.93,"122":13.06,"123":10.97,"124":27.02,"125":22.13,"126":29.28,"127":14.72,"128":28.87,"129":194.95,"130":43.87,"131":60.11,"132":32.31,"133":36.47,"134":81.6,"135":200.56,"136":64.21,"137":19.43,"138":57.97,"139":178.06,"140":33.24,"141":17.94,"142":29.5,"143":30.73,"144":99.63,"145":110.52,"146":80.07,"147":83.99,"148":34.74,"149":73.71,"150":26.62,"151":44.55,"152":25.81,"153":141.88,"154":112.56,"155":11.76,"156":17.04,"157":182.5,"158":53.68,"159":69.87,"160":26.0,"161":17.3,"162":41.81,"163":17.18,"164":26.14,"165":38.08,"166":157.65,"167":15.67,"168":51.27,"169":118.75,"170":76.28,"171":39.48,"172":49.98,"173":25.72,"174":18.78,"175":50.23,"176":70.35,"177":77.17,"178":11.3,"179":13.86,"180":56.11,"181":61.01,"182":138.95,"183":102.47,"184":15.01,"185":44.36,"186":21.71,"187":28.81},"20-day SMA":{"0":46.16,"1":375.29,"2":24.45,"3":94.71,"4":11.48,"5":15.51,"6":24.27,"7":149.61,"8":17.08,"9":110.75,"10":63.57,"11":11.39,"12":11.05,"13":35.83,"14":11.54,"15":76.46,"16":15.19,"17":18.98,"18":62.5,"19":542.31,"20":363.69,"21":16.1,"22":32.41,"23":39.84,"24":30.99,"25":42.53,"26":51.52,"27":14.96,"28":14.97,"29":166.81,"30":51.24,"31":33.58,"32":15.03,"33":93.07,"34":20.99,"35":18.84,"36":20.61,"37":114.81,"38":77.78,"39":18.64,"40":65.41,"41":14.65,"42":27.25,"43":41.1,"44":36.85,"45":37.93,"46":290.55,"47":73.38,"48":111.09,"49":57.03,"50":53.34,"51":35.7,"52":39.06,"53":82.48,"54":24.98,"55":541.2,"56":81.44,"57":15.48,"58":29.5,"59":58.2,"60":122.44,"61":46.72,"62":29.63,"63":40.63,"64":37.41,"65":15.4,"66":32.07,"67":10.86,"68":75.07,"69":113.78,"70":642.9,"71":54.96,"72":40.03,"73":26.22,"74":36.21,"75":36.7,"76":58.36,"77":19.94,"78":27.84,"79":45.79,"80":17.7,"81":60.54,"82":28.84,"83":27.99,"84":181.01,"85":108.99,"86":43.4,"87":107.88,"88":445.41,"89":19.81,"90":88.67,"91":9.31,"92":10.65,"93":21.52,"94":13.24,"95":39.1,"96":132.61,"97":21.9,"98":95.63,"99":46.61,"100":301.56,"101":27.07,"102":407.21,"103":83.15,"104":22.16,"105":43.84,"106":45.46,"107":16.6,"108":1338.68,"109":27.92,"110":111.32,"111":820.96,"112":10.93,"113":98.73,"114":43.06,"115":45.37,"116":886.77,"117":89.79,"118":13.28,"119":54.18,"120":11.32,"121":43.87,"122":12.89,"123":10.89,"124":24.91,"125":21.66,"126":28.15,"127":14.47,"128":27.53,"129":190.7,"130":42.26,"131":58.32,"132":31.51,"133":35.32,"134":79.83,"135":195.5,"136":62.76,"137":18.52,"138":49.41,"139":174.14,"140":25.35,"141":17.53,"142":28.63,"143":28.07,"144":96.27,"145":94.57,"146":76.38,"147":83.66,"148":34.43,"149":70.36,"150":25.77,"151":43.84,"152":25.72,"153":139.13,"154":111.13,"155":11.46,"156":16.49,"157":180.2,"158":53.23,"159":62.32,"160":25.6,"161":17.02,"162":41.36,"163":16.83,"164":25.6,"165":37.79,"166":150.63,"167":15.19,"168":48.52,"169":115.17,"170":73.83,"171":39.33,"172":45.54,"173":25.56,"174":18.53,"175":48.28,"176":68.19,"177":74.03,"178":10.55,"179":13.31,"180":54.87,"181":58.7,"182":137.05,"183":101.97,"184":14.48,"185":39.85,"186":20.99,"187":28.73},"50-day SMA":{"0":43.06,"1":331.27,"2":21.89,"3":90.92,"4":9.82,"5":11.94,"6":18.36,"7":144.61,"8":13.51,"9":99.66,"10":55.51,"11":9.56,"12":10.13,"13":33.97,"14":11.15,"15":72.92,"16":14.09,"17":18.54,"18":56.46,"19":522.16,"20":308.65,"21":14.29,"22":29.98,"23":36.85,"24":27.92,"25":38.24,"26":44.15,"27":13.59,"28":14.19,"29":157.48,"30":43.95,"31":30.08,"32":12.24,"33":72.62,"34":20.88,"35":17.34,"36":18.67,"37":110.96,"38":73.1,"39":16.72,"40":63.15,"41":11.99,"42":25.74,"43":36.98,"44":30.65,"45":26.22,"46":247.26,"47":70.97,"48":101.57,"49":55.51,"50":48.79,"51":29.78,"52":33.44,"53":75.04,"54":22.49,"55":508.99,"56":81.18,"57":15.05,"58":27.72,"59":53.24,"60":120.06,"61":40.61,"62":26.73,"63":38.29,"64":33.84,"65":13.39,"66":30.36,"67":10.53,"68":69.09,"69":107.11,"70":624.44,"71":51.28,"72":37.07,"73":24.83,"74":34.43,"75":34.11,"76":51.46,"77":18.75,"78":25.8,"79":41.94,"80":14.41,"81":56.19,"82":28.52,"83":25.63,"84":167.17,"85":103.34,"86":42.62,"87":96.81,"88":409.66,"89":16.15,"90":81.98,"91":8.73,"92":9.75,"93":19.91,"94":12.39,"95":38.23,"96":123.35,"97":19.06,"98":90.93,"99":42.79,"100":281.67,"101":23.97,"102":371.0,"103":77.12,"104":19.36,"105":40.26,"106":41.26,"107":12.85,"108":1297.93,"109":26.74,"110":108.59,"111":797.49,"112":9.34,"113":92.15,"114":40.68,"115":42.56,"116":833.02,"117":81.52,"118":13.1,"119":39.93,"120":10.65,"121":38.56,"122":12.31,"123":9.16,"124":22.44,"125":20.54,"126":25.15,"127":13.48,"128":25.92,"129":178.69,"130":40.45,"131":56.36,"132":25.14,"133":31.4,"134":74.85,"135":195.39,"136":59.34,"137":17.31,"138":37.97,"139":171.68,"140":19.27,"141":15.77,"142":26.53,"143":25.8,"144":85.35,"145":81.68,"146":72.66,"147":76.98,"148":32.48,"149":63.76,"150":24.96,"151":35.62,"152":23.37,"153":129.27,"154":107.19,"155":10.68,"156":15.18,"157":169.92,"158":46.61,"159":57.83,"160":22.53,"161":15.33,"162":37.79,"163":16.46,"164":23.69,"165":34.62,"166":147.3,"167":13.71,"168":42.75,"169":107.27,"170":67.67,"171":36.96,"172":40.94,"173":23.12,"174":16.76,"175":43.29,"176":56.14,"177":66.61,"178":9.28,"179":11.91,"180":53.72,"181":52.71,"182":123.71,"183":94.43,"184":12.16,"185":34.43,"186":19.48,"187":26.91},"200-day SMA":{"0":43.19,"1":270.84,"2":16.88,"3":85.53,"4":7.56,"5":10.05,"6":20.15,"7":126.88,"8":8.55,"9":68.2,"10":41.0,"11":8.48,"12":8.01,"13":25.79,"14":10.55,"15":68.73,"16":12.56,"17":12.97,"18":39.2,"19":390.62,"20":280.05,"21":12.38,"22":25.94,"23":32.05,"24":17.72,"25":34.66,"26":39.41,"27":10.81,"28":11.84,"29":134.84,"30":28.48,"31":29.05,"32":11.06,"33":60.49,"34":16.87,"35":8.32,"36":18.54,"37":92.74,"38":58.35,"39":14.01,"40":47.27,"41":6.78,"42":17.57,"43":24.18,"44":27.8,"45":13.35,"46":129.92,"47":57.93,"48":81.83,"49":43.44,"50":42.17,"51":25.34,"52":25.45,"53":61.03,"54":14.44,"55":435.33,"56":71.65,"57":13.88,"58":23.83,"59":39.16,"60":88.99,"61":33.96,"62":19.03,"63":36.15,"64":24.94,"65":11.35,"66":23.09,"67":8.16,"68":56.15,"69":75.81,"70":508.13,"71":39.93,"72":29.3,"73":21.05,"74":30.86,"75":26.68,"76":41.93,"77":17.03,"78":21.55,"79":37.45,"80":10.41,"81":48.71,"82":27.31,"83":17.16,"84":131.49,"85":84.89,"86":33.23,"87":86.94,"88":254.84,"89":12.77,"90":69.08,"91":7.15,"92":8.34,"93":16.44,"94":9.64,"95":36.48,"96":101.0,"97":17.32,"98":65.03,"99":36.01,"100":190.88,"101":19.52,"102":244.35,"103":59.58,"104":14.33,"105":36.85,"106":36.25,"107":9.16,"108":944.85,"109":22.84,"110":85.81,"111":669.85,"112":9.84,"113":77.6,"114":33.15,"115":33.44,"116":635.87,"117":60.66,"118":10.64,"119":21.27,"120":9.33,"121":32.9,"122":11.38,"123":7.45,"124":16.82,"125":16.93,"126":24.6,"127":10.79,"128":20.21,"129":133.04,"130":40.79,"131":46.21,"132":22.31,"133":23.69,"134":57.4,"135":179.24,"136":45.6,"137":14.4,"138":22.55,"139":134.16,"140":13.42,"141":13.49,"142":23.15,"143":19.89,"144":72.91,"145":65.16,"146":76.63,"147":62.62,"148":27.86,"149":65.0,"150":20.98,"151":32.41,"152":18.54,"153":90.05,"154":85.86,"155":9.96,"156":9.66,"157":118.42,"158":42.21,"159":53.19,"160":16.16,"161":11.74,"162":35.03,"163":13.93,"164":18.29,"165":29.05,"166":124.6,"167":13.55,"168":39.29,"169":93.73,"170":53.75,"171":22.38,"172":30.79,"173":18.84,"174":17.72,"175":37.67,"176":43.26,"177":56.27,"178":9.16,"179":9.96,"180":35.8,"181":37.78,"182":111.28,"183":69.68,"184":8.03,"185":27.51,"186":17.01,"187":25.49},"52-week high":{"0":56.47,"1":431.99,"2":27.67,"3":98.24,"4":12.5,"5":25.91,"6":40.86,"7":194.21,"8":20.65,"9":167.24,"10":72.85,"11":16.75,"12":12.01,"13":41.22,"14":12.05,"15":85.72,"16":16.69,"17":20.55,"18":71.72,"19":571.59,"20":394.3,"21":21.41,"22":33.99,"23":45.3,"24":33.77,"25":47.98,"26":60.72,"27":16.19,"28":16.5,"29":172.54,"30":59.24,"31":36.15,"32":21.66,"33":116.3,"34":25.13,"35":20.69,"36":24.04,"37":120.82,"38":80.58,"39":20.41,"40":71.43,"41":18.01,"42":30.91,"43":45.98,"44":45.0,"45":58.05,"46":337.79,"47":76.93,"48":115.25,"49":59.26,"50":65.99,"51":43.93,"52":39.54,"53":90.86,"54":27.28,"55":562.97,"56":85.85,"57":20.65,"58":37.39,"59":60.58,"60":131.8,"61":47.11,"62":32.45,"63":43.68,"64":42.83,"65":16.52,"66":34.33,"67":11.99,"68":78.21,"69":120.61,"70":724.07,"71":57.2,"72":41.99,"73":29.36,"74":41.52,"75":40.5,"76":62.59,"77":32.97,"78":28.78,"79":56.19,"80":21.8,"81":65.64,"82":33.73,"83":40.56,"84":195.9,"85":113.34,"86":49.37,"87":115.37,"88":480.88,"89":26.3,"90":99.63,"91":10.48,"92":11.47,"93":23.34,"94":15.03,"95":46.85,"96":143.67,"97":23.81,"98":100.77,"99":48.86,"100":326.2,"101":28.6,"102":439.0,"103":91.66,"104":24.98,"105":47.17,"106":47.36,"107":19.88,"108":1457.98,"109":28.9,"110":123.83,"111":860.0,"112":15.27,"113":105.39,"114":45.63,"115":48.43,"116":923.18,"117":100.57,"118":14.55,"119":63.4,"120":12.35,"121":58.62,"122":14.45,"123":11.73,"124":30.03,"125":22.69,"126":31.11,"127":15.73,"128":31.32,"129":205.08,"130":49.0,"131":63.52,"132":39.0,"133":38.08,"134":86.01,"135":232.0,"136":67.99,"137":21.56,"138":67.22,"139":189.15,"140":36.36,"141":19.15,"142":30.94,"143":33.99,"144":102.66,"145":133.09,"146":106.38,"147":85.85,"148":36.11,"149":80.0,"150":27.73,"151":45.5,"152":26.98,"153":149.21,"154":117.96,"155":12.11,"156":19.0,"157":193.69,"158":54.3,"159":98.38,"160":27.03,"161":18.34,"162":42.81,"163":18.48,"164":27.85,"165":39.19,"166":167.0,"167":17.02,"168":52.74,"169":122.76,"170":80.28,"171":48.87,"172":54.0,"173":27.44,"174":25.49,"175":53.05,"176":76.35,"177":83.24,"178":11.99,"179":14.4,"180":59.3,"181":63.72,"182":144.86,"183":112.95,"184":17.68,"185":48.15,"186":22.74,"187":31.38}}